ab5/__init__.py
ab5-0.7.dist-info/LICENSE
ab5-0.7.dist-info/METADATA
ab5-0.7.dist-info/WHEEL
ab5-0.7.dist-info/top_level.txt
ab5-0.7.dist-info/RECORD
