Metadata-Version: 2.1
Name: ab5
Version: 0.7
Summary: print ascii art with gratient colors
Home-page: https://github.com/xxa2005/
Author: Ab.5#3363
License: UNKNOWN
Keywords: color,python,colors,cool,gratient,fade,shadow
Platform: UNKNOWN
Classifier: Intended Audience :: Developers
Classifier: Programming Language :: Python :: 3
Classifier: License :: OSI Approved :: MIT License
Classifier: Operating System :: OS Independent
License-File: LICENSE
